aseafile/__init__.py
aseafile/exceptions.py
aseafile/http_client.py
aseafile/py.typed
aseafile/route_storage.py
aseafile/builders/__init__.py
aseafile/builders/query_params_builder.py
aseafile/enums/__init__.py
aseafile/enums/dir_operations.py
aseafile/enums/file_operation.py
aseafile/enums/http_methods.py
aseafile/enums/item_type.py
aseafile/enums/repo_type.py
aseafile/enums/base/__init__.py
aseafile/enums/base/strenum.py
aseafile/http_handlers/__init__.py
aseafile/http_handlers/base_http_handler.py
aseafile/http_handlers/http_download_handler.py
aseafile/http_handlers/http_request_handler.py
aseafile/models/__init__.py
aseafile/models/base_item.py
aseafile/models/dir_item.py
aseafile/models/dir_item_detail.py
aseafile/models/error.py
aseafile/models/file_item.py
aseafile/models/file_item_detail.py
aseafile/models/repo_item.py
aseafile/models/sea_result.py
aseafile/models/search_result.py
aseafile/models/search_result_item.py
aseafile/models/smart_link.py
aseafile/models/token_container.py
aseafile/models/upload_file.py
aseafile/models/uploaded_file_item.py
aseafile-0.1.6a0.dist-info/LICENSE.txt
aseafile-0.1.6a0.dist-info/METADATA
aseafile-0.1.6a0.dist-info/WHEEL
aseafile-0.1.6a0.dist-info/top_level.txt
aseafile-0.1.6a0.dist-info/RECORD
