Metadata-Version: 2.1
Name: aseafile
Version: 0.1.6a0
Summary: Unofficial library that provides the API methods of the seafile service
Home-page: https://github.com/Gwinkamp/aseafile
Author: Gwinkamp
Author-email: Aleksey-Y-Kiryutin@yandex.ru
License: MIT
Keywords: seafile
Classifier: Topic :: Internet :: WWW/HTTP
Classifier: Programming Language :: Python :: 3.10
Classifier: Framework :: aiohttp
Requires-Python: >=3.10
License-File: LICENSE.txt
Requires-Dist: aiohttp
Requires-Dist: pydantic
